qlasso/__init__.py
qlasso/definitions.py
qlasso/gss.py
qlasso/qlasso_instance.py
qlasso/qlasso_solvers.py
qlasso/data/t10k-images-idx3-ubyte.gz
qlasso/data/t10k-labels-idx1-ubyte.gz
qlasso/data/train-images-idx3-ubyte.gz
qlasso/data/train-labels-idx1-ubyte.gz
qlasso-0.0.2.dist-info/METADATA
qlasso-0.0.2.dist-info/WHEEL
qlasso-0.0.2.dist-info/licenses/LICENSE
qlasso-0.0.2.dist-info/RECORD
