Metadata-Version: 2.1
Name: qlasso
Version: 0.0.2
Summary: A package implementing algorithms and screening rules for the quadratic LASSO problem
Project-URL: Homepage, https://gitlab.com/gsagnol/qlasso
Author-email: Guillaume Sagnol <sagnol@math.tu-berlin.de>
License-File: LICENSE
Classifier: License :: OSI Approved :: MIT License
Classifier: Operating System :: OS Independent
Classifier: Programming Language :: Python :: 3
Requires-Python: >=3.7
Requires-Dist: matplotlib
Requires-Dist: numpy
Requires-Dist: opencv-python
Requires-Dist: picos
Requires-Dist: scipy
